redishilok/__init__.py
redishilok/hilok.py
redishilok/py.typed
redishilok/rwctx.py
redishilok/rwlock.py
redishilok/types.py
redishilok-1.1.0.dist-info/METADATA
redishilok-1.1.0.dist-info/WHEEL
redishilok-1.1.0.dist-info/RECORD
