Metadata-Version: 2.1
Name: redishilok
Version: 1.1.0
Summary: Redis-based read-write distributed and hierarchical locking library
Home-page: https://github.com/puzzlefin/redishilok
License: MIT
Keywords: redis,locking,distributed-locking,hierarchical-locking,python
Author: Erik Aronesty
Author-email: erik@q32.com
Requires-Python: >=3.11,<4.0
Classifier: Development Status :: 3 - Alpha
Classifier: Intended Audience :: Developers
Classifier: License :: OSI Approved :: MIT License
Classifier: Programming Language :: Python
Classifier: Programming Language :: Python :: 3
Classifier: Programming Language :: Python :: 3.11
Classifier: Programming Language :: Python :: 3.12
Classifier: Topic :: Software Development :: Libraries
Classifier: Topic :: System :: Distributed Computing
Classifier: Topic :: Utilities
Requires-Dist: redis[hiredis] (>=5.2.0,<6.0.0)
Project-URL: Repository, https://github.com/puzzlefin/redishilok
